LICENSE
MANIFEST.in
README.md
setup.py
chgender/__init__.py
chgender/batch.py
chgender/chgender.py
chgender/chinese_name_lib.txt
chgender/pinyin_dataset.txt
chgender.egg-info/PKG-INFO
chgender.egg-info/SOURCES.txt
chgender.egg-info/dependency_links.txt
chgender.egg-info/entry_points.txt
chgender.egg-info/top_level.txt
test/test.py