Metadata-Version: 1.1
Name: chgender
Version: 0.0.2
Summary: Gender gusser for Chinese names in English (pinyin) form
Home-page: https://github.com/jiajianzhou/chgender
Author: Jiajian Zhou
Author-email: jiajianzhou0808@gmail.com
License: MIT License
Keywords: gender name guess python
Platform: UNKNOWN
Classifier: Development Status :: 4 - Beta
Classifier: Intended Audience :: Developers
Classifier: Natural Language :: English
Classifier: License :: OSI Approved :: MIT License
Classifier: Programming Language :: Python
